<?xml version="1.0" encoding="Windows-1252"?>
<!DOCTYPE POWERMART SYSTEM "powrmart.dtd">
<POWERMART CREATION_DATE="02/16/2018 09:00:06" REPOSITORY_VERSION="184.93">
<REPOSITORY NAME="BIBO13DECREPO" VERSION="184" CODEPAGE="MS1252" DATABASETYPE="Oracle">
<FOLDER NAME="INF2" GROUP="" OWNER="TRG2" SHARED="NOTSHARED" DESCRIPTION="" PERMISSIONS="rwx------" UUID="f90f6354-0c48-415a-a1e6-fcd0f082d842">
    <SOURCE BUSINESSNAME ="" DATABASETYPE ="Flat File" DBDNAME ="FlatFile" DESCRIPTION ="" NAME ="Copy_of_Census_data" OBJECTVERSION ="1" OWNERNAME ="" VERSIONNUMBER ="1">
        <FLATFILE CODEPAGE ="MS1252" CONSECDELIMITERSASONE ="NO" DELIMITED ="YES" DELIMITERS ="," ESCAPE_CHARACTER ="" KEEPESCAPECHAR ="NO" LINESEQUENTIAL ="NO" MULTIDELIMITERSASAND ="YES" NULLCHARTYPE ="ASCII" NULL_CHARACTER ="*" PADBYTES ="1" QUOTE_CHARACTER ="DOUBLE" REPEATABLE ="NO" ROWDELIMITER ="0" SHIFTSENSITIVEDATA ="NO" SKIPROWS ="1" STRIPTRAILINGBLANKS ="NO"/>
        <TABLEATTRIBUTE NAME ="Base Table Name" VALUE =""/>
        <TABLEATTRIBUTE NAME ="Search Specification" VALUE =""/>
        <TABLEATTRIBUTE NAME ="Sort Specification" VALUE =""/>
        <TABLEATTRIBUTE NAME ="Datetime Format" VALUE ="A  19 mm/dd/yyyy hh24:mi:ss"/>
        <TABLEATTRIBUTE NAME ="Thousand Separator" VALUE ="None"/>
        <TABLEATTRIBUTE NAME ="Decimal Separator" VALUE ="."/>
        <TABLEATTRIBUTE NAME ="Add Currently Processed Flat File Name Port" VALUE ="NO"/>
        <SOURCEFIELD BUSINESSNAME ="" DATATYPE ="string" DESCRIPTION ="" FIELDNUMBER ="1" FIELDPROPERTY ="0" FIELDTYPE ="ELEMITEM" HIDDEN ="NO" KEYTYPE ="NOT A KEY" LENGTH ="4" LEVEL ="0" NAME ="PERSON_ID" NULLABLE ="NULL" OCCURS ="0" OFFSET ="0" PHYSICALLENGTH ="4" PHYSICALOFFSET ="0" PICTURETEXT ="" PRECISION ="4" SCALE ="0" USAGE_FLAGS =""/>
        <SOURCEFIELD BUSINESSNAME ="" DATATYPE ="number" DESCRIPTION ="" FIELDNUMBER ="2" FIELDPROPERTY ="0" FIELDTYPE ="ELEMITEM" HIDDEN ="NO" KEYTYPE ="NOT A KEY" LENGTH ="4" LEVEL ="0" NAME ="DOOR_NUMBER" NULLABLE ="NULL" OCCURS ="0" OFFSET ="4" PHYSICALLENGTH ="4" PHYSICALOFFSET ="4" PICTURETEXT ="" PRECISION ="4" SCALE ="0" USAGE_FLAGS =""/>
        <SOURCEFIELD BUSINESSNAME ="" DATATYPE ="string" DESCRIPTION ="" FIELDNUMBER ="3" FIELDPROPERTY ="0" FIELDTYPE ="ELEMITEM" HIDDEN ="NO" KEYTYPE ="NOT A KEY" LENGTH ="6" LEVEL ="0" NAME ="GENDER" NULLABLE ="NULL" OCCURS ="0" OFFSET ="8" PHYSICALLENGTH ="6" PHYSICALOFFSET ="8" PICTURETEXT ="" PRECISION ="6" SCALE ="0" USAGE_FLAGS =""/>
        <SOURCEFIELD BUSINESSNAME ="" DATATYPE ="string" DESCRIPTION ="" FIELDNUMBER ="4" FIELDPROPERTY ="0" FIELDTYPE ="ELEMITEM" HIDDEN ="NO" KEYTYPE ="NOT A KEY" LENGTH ="12" LEVEL ="0" NAME ="DOB" NULLABLE ="NULL" OCCURS ="0" OFFSET ="14" PHYSICALLENGTH ="12" PHYSICALOFFSET ="14" PICTURETEXT ="" PRECISION ="12" SCALE ="0" USAGE_FLAGS =""/>
        <SOURCEFIELD BUSINESSNAME ="" DATATYPE ="string" DESCRIPTION ="" FIELDNUMBER ="5" FIELDPROPERTY ="0" FIELDTYPE ="ELEMITEM" HIDDEN ="NO" KEYTYPE ="NOT A KEY" LENGTH ="9" LEVEL ="0" NAME ="CURRENT_MARRTIAL_STATUS" NULLABLE ="NULL" OCCURS ="0" OFFSET ="26" PHYSICALLENGTH ="9" PHYSICALOFFSET ="26" PICTURETEXT ="" PRECISION ="9" SCALE ="0" USAGE_FLAGS =""/>
        <SOURCEFIELD BUSINESSNAME ="" DATATYPE ="string" DESCRIPTION ="" FIELDNUMBER ="6" FIELDPROPERTY ="0" FIELDTYPE ="ELEMITEM" HIDDEN ="NO" KEYTYPE ="NOT A KEY" LENGTH ="9" LEVEL ="0" NAME ="RELIGION" NULLABLE ="NULL" OCCURS ="0" OFFSET ="35" PHYSICALLENGTH ="9" PHYSICALOFFSET ="35" PICTURETEXT ="" PRECISION ="9" SCALE ="0" USAGE_FLAGS =""/>
        <SOURCEFIELD BUSINESSNAME ="" DATATYPE ="string" DESCRIPTION ="" FIELDNUMBER ="7" FIELDPROPERTY ="0" FIELDTYPE ="ELEMITEM" HIDDEN ="NO" KEYTYPE ="NOT A KEY" LENGTH ="5" LEVEL ="0" NAME ="CASTE" NULLABLE ="NULL" OCCURS ="0" OFFSET ="44" PHYSICALLENGTH ="5" PHYSICALOFFSET ="44" PICTURETEXT ="" PRECISION ="5" SCALE ="0" USAGE_FLAGS =""/>
        <SOURCEFIELD BUSINESSNAME ="" DATATYPE ="string" DESCRIPTION ="" FIELDNUMBER ="8" FIELDPROPERTY ="0" FIELDTYPE ="ELEMITEM" HIDDEN ="NO" KEYTYPE ="NOT A KEY" LENGTH ="3" LEVEL ="0" NAME ="DISABILITY" NULLABLE ="NULL" OCCURS ="0" OFFSET ="49" PHYSICALLENGTH ="3" PHYSICALOFFSET ="49" PICTURETEXT ="" PRECISION ="3" SCALE ="0" USAGE_FLAGS =""/>
        <SOURCEFIELD BUSINESSNAME ="" DATATYPE ="string" DESCRIPTION ="" FIELDNUMBER ="9" FIELDPROPERTY ="0" FIELDTYPE ="ELEMITEM" HIDDEN ="NO" KEYTYPE ="NOT A KEY" LENGTH ="19" LEVEL ="0" NAME ="TYPE_OF_DISABILITY" NULLABLE ="NULL" OCCURS ="0" OFFSET ="52" PHYSICALLENGTH ="19" PHYSICALOFFSET ="52" PICTURETEXT ="" PRECISION ="19" SCALE ="0" USAGE_FLAGS =""/>
        <SOURCEFIELD BUSINESSNAME ="" DATATYPE ="string" DESCRIPTION ="" FIELDNUMBER ="10" FIELDPROPERTY ="0" FIELDTYPE ="ELEMITEM" HIDDEN ="NO" KEYTYPE ="NOT A KEY" LENGTH ="10" LEVEL ="0" NAME ="LITERACY_STATUS" NULLABLE ="NULL" OCCURS ="0" OFFSET ="71" PHYSICALLENGTH ="10" PHYSICALOFFSET ="71" PICTURETEXT ="" PRECISION ="10" SCALE ="0" USAGE_FLAGS =""/>
        <SOURCEFIELD BUSINESSNAME ="" DATATYPE ="string" DESCRIPTION ="" FIELDNUMBER ="11" FIELDPROPERTY ="0" FIELDTYPE ="ELEMITEM" HIDDEN ="NO" KEYTYPE ="NOT A KEY" LENGTH ="10" LEVEL ="0" NAME ="CURRENTSTATUS_OF_ATTENDANCE" NULLABLE ="NULL" OCCURS ="0" OFFSET ="81" PHYSICALLENGTH ="10" PHYSICALOFFSET ="81" PICTURETEXT ="" PRECISION ="10" SCALE ="0" USAGE_FLAGS =""/>
        <SOURCEFIELD BUSINESSNAME ="" DATATYPE ="string" DESCRIPTION ="" FIELDNUMBER ="12" FIELDPROPERTY ="0" FIELDTYPE ="ELEMITEM" HIDDEN ="NO" KEYTYPE ="NOT A KEY" LENGTH ="3" LEVEL ="0" NAME ="HIGHEST_EDUCATION_LEVEL" NULLABLE ="NULL" OCCURS ="0" OFFSET ="91" PHYSICALLENGTH ="3" PHYSICALOFFSET ="91" PICTURETEXT ="" PRECISION ="3" SCALE ="0" USAGE_FLAGS =""/>
        <SOURCEFIELD BUSINESSNAME ="" DATATYPE ="string" DESCRIPTION ="" FIELDNUMBER ="13" FIELDPROPERTY ="0" FIELDTYPE ="ELEMITEM" HIDDEN ="NO" KEYTYPE ="NOT A KEY" LENGTH ="17" LEVEL ="0" NAME ="OCCUPATION" NULLABLE ="NULL" OCCURS ="0" OFFSET ="94" PHYSICALLENGTH ="17" PHYSICALOFFSET ="94" PICTURETEXT ="" PRECISION ="17" SCALE ="0" USAGE_FLAGS =""/>
        <SOURCEFIELD BUSINESSNAME ="" DATATYPE ="string" DESCRIPTION ="" FIELDNUMBER ="14" FIELDPROPERTY ="0" FIELDTYPE ="ELEMITEM" HIDDEN ="NO" KEYTYPE ="NOT A KEY" LENGTH ="19" LEVEL ="0" NAME ="NATURE_OF_INDUSTRY" NULLABLE ="NULL" OCCURS ="0" OFFSET ="111" PHYSICALLENGTH ="19" PHYSICALOFFSET ="111" PICTURETEXT ="" PRECISION ="19" SCALE ="0" USAGE_FLAGS =""/>
        <SOURCEFIELD BUSINESSNAME ="" DATATYPE ="string" DESCRIPTION ="" FIELDNUMBER ="15" FIELDPROPERTY ="0" FIELDTYPE ="ELEMITEM" HIDDEN ="NO" KEYTYPE ="NOT A KEY" LENGTH ="13" LEVEL ="0" NAME ="SECTOR" NULLABLE ="NULL" OCCURS ="0" OFFSET ="130" PHYSICALLENGTH ="13" PHYSICALOFFSET ="130" PICTURETEXT ="" PRECISION ="13" SCALE ="0" USAGE_FLAGS =""/>
        <SOURCEFIELD BUSINESSNAME ="" DATATYPE ="number" DESCRIPTION ="" FIELDNUMBER ="16" FIELDPROPERTY ="0" FIELDTYPE ="ELEMITEM" HIDDEN ="NO" KEYTYPE ="NOT A KEY" LENGTH ="10" LEVEL ="0" NAME ="SALARY" NULLABLE ="NULL" OCCURS ="0" OFFSET ="143" PHYSICALLENGTH ="10" PHYSICALOFFSET ="143" PICTURETEXT ="" PRECISION ="10" SCALE ="0" USAGE_FLAGS =""/>
        <SOURCEFIELD BUSINESSNAME ="" DATATYPE ="string" DESCRIPTION ="" FIELDNUMBER ="17" FIELDPROPERTY ="0" FIELDTYPE ="ELEMITEM" HIDDEN ="NO" KEYTYPE ="NOT A KEY" LENGTH ="7" LEVEL ="0" NAME ="MODE_OF_TRAVELLING_TO_WORK_PLACE" NULLABLE ="NULL" OCCURS ="0" OFFSET ="153" PHYSICALLENGTH ="7" PHYSICALOFFSET ="153" PICTURETEXT ="" PRECISION ="7" SCALE ="0" USAGE_FLAGS =""/>
        <SOURCEFIELD BUSINESSNAME ="" DATATYPE ="string" DESCRIPTION ="" FIELDNUMBER ="18" FIELDPROPERTY ="0" FIELDTYPE ="ELEMITEM" HIDDEN ="NO" KEYTYPE ="NOT A KEY" LENGTH ="2" LEVEL ="0" NAME ="CHILDREN_SURVIVING" NULLABLE ="NULL" OCCURS ="0" OFFSET ="160" PHYSICALLENGTH ="2" PHYSICALOFFSET ="160" PICTURETEXT ="" PRECISION ="2" SCALE ="0" USAGE_FLAGS =""/>
        <SOURCEFIELD BUSINESSNAME ="" DATATYPE ="string" DESCRIPTION ="" FIELDNUMBER ="19" FIELDPROPERTY ="0" FIELDTYPE ="ELEMITEM" HIDDEN ="NO" KEYTYPE ="NOT A KEY" LENGTH ="2" LEVEL ="0" NAME ="CHILDREN_EVER_BORN" NULLABLE ="NULL" OCCURS ="0" OFFSET ="162" PHYSICALLENGTH ="2" PHYSICALOFFSET ="162" PICTURETEXT ="" PRECISION ="2" SCALE ="0" USAGE_FLAGS =""/>
        <SOURCEFIELD BUSINESSNAME ="" DATATYPE ="number" DESCRIPTION ="" FIELDNUMBER ="20" FIELDPROPERTY ="0" FIELDTYPE ="ELEMITEM" HIDDEN ="NO" KEYTYPE ="NOT A KEY" LENGTH ="1" LEVEL ="0" NAME ="NUMBER_OF_PERSONS_EXPIRED_IN_LAST_10_YEARS" NULLABLE ="NULL" OCCURS ="0" OFFSET ="164" PHYSICALLENGTH ="1" PHYSICALOFFSET ="164" PICTURETEXT ="" PRECISION ="1" SCALE ="0" USAGE_FLAGS =""/>
        <SOURCEFIELD BUSINESSNAME ="" DATATYPE ="string" DESCRIPTION ="" FIELDNUMBER ="21" FIELDPROPERTY ="0" FIELDTYPE ="ELEMITEM" HIDDEN ="NO" KEYTYPE ="NOT A KEY" LENGTH ="4" LEVEL ="0" NAME ="TYPE_OF_HOUSE" NULLABLE ="NULL" OCCURS ="0" OFFSET ="165" PHYSICALLENGTH ="4" PHYSICALOFFSET ="165" PICTURETEXT ="" PRECISION ="4" SCALE ="0" USAGE_FLAGS =""/>
        <SOURCEFIELD BUSINESSNAME ="" DATATYPE ="string" DESCRIPTION ="" FIELDNUMBER ="22" FIELDPROPERTY ="0" FIELDTYPE ="ELEMITEM" HIDDEN ="NO" KEYTYPE ="NOT A KEY" LENGTH ="3" LEVEL ="0" NAME ="PAN_CARD" NULLABLE ="NULL" OCCURS ="0" OFFSET ="169" PHYSICALLENGTH ="3" PHYSICALOFFSET ="169" PICTURETEXT ="" PRECISION ="3" SCALE ="0" USAGE_FLAGS =""/>
        <SOURCEFIELD BUSINESSNAME ="" DATATYPE ="string" DESCRIPTION ="" FIELDNUMBER ="23" FIELDPROPERTY ="0" FIELDTYPE ="ELEMITEM" HIDDEN ="NO" KEYTYPE ="NOT A KEY" LENGTH ="3" LEVEL ="0" NAME ="RATION_CARD" NULLABLE ="NULL" OCCURS ="0" OFFSET ="172" PHYSICALLENGTH ="3" PHYSICALOFFSET ="172" PICTURETEXT ="" PRECISION ="3" SCALE ="0" USAGE_FLAGS =""/>
        <SOURCEFIELD BUSINESSNAME ="" DATATYPE ="string" DESCRIPTION ="" FIELDNUMBER ="24" FIELDPROPERTY ="0" FIELDTYPE ="ELEMITEM" HIDDEN ="NO" KEYTYPE ="NOT A KEY" LENGTH ="3" LEVEL ="0" NAME ="ADHAR_CARD" NULLABLE ="NULL" OCCURS ="0" OFFSET ="175" PHYSICALLENGTH ="3" PHYSICALOFFSET ="175" PICTURETEXT ="" PRECISION ="3" SCALE ="0" USAGE_FLAGS =""/>
        <SOURCEFIELD BUSINESSNAME ="" DATATYPE ="string" DESCRIPTION ="" FIELDNUMBER ="25" FIELDPROPERTY ="0" FIELDTYPE ="ELEMITEM" HIDDEN ="NO" KEYTYPE ="NOT A KEY" LENGTH ="13" LEVEL ="0" NAME ="AREA" NULLABLE ="NULL" OCCURS ="0" OFFSET ="178" PHYSICALLENGTH ="13" PHYSICALOFFSET ="178" PICTURETEXT ="" PRECISION ="13" SCALE ="0" USAGE_FLAGS =""/>
        <SOURCEFIELD BUSINESSNAME ="" DATATYPE ="string" DESCRIPTION ="" FIELDNUMBER ="26" FIELDPROPERTY ="0" FIELDTYPE ="ELEMITEM" HIDDEN ="NO" KEYTYPE ="NOT A KEY" LENGTH ="9" LEVEL ="0" NAME ="CITY" NULLABLE ="NULL" OCCURS ="0" OFFSET ="191" PHYSICALLENGTH ="9" PHYSICALOFFSET ="191" PICTURETEXT ="" PRECISION ="9" SCALE ="0" USAGE_FLAGS =""/>
    </SOURCE>
    <TARGET BUSINESSNAME ="" CONSTRAINT ="" DATABASETYPE ="Oracle" DESCRIPTION ="" NAME ="CENSUS_DATA_TGT_STG" OBJECTVERSION ="1" TABLEOPTIONS ="" VERSIONNUMBER ="1">
        <TARGETFIELD BUSINESSNAME ="" DATATYPE ="varchar2" DESCRIPTION ="" FIELDNUMBER ="1" KEYTYPE ="NOT A KEY" NAME ="PERSON_ID" NULLABLE ="NULL" PICTURETEXT ="" PRECISION ="4" SCALE ="0"/>
        <TARGETFIELD BUSINESSNAME ="" DATATYPE ="number(p,s)" DESCRIPTION ="" FIELDNUMBER ="2" KEYTYPE ="NOT A KEY" NAME ="DOOR_NUMBER" NULLABLE ="NULL" PICTURETEXT ="" PRECISION ="4" SCALE ="0"/>
        <TARGETFIELD BUSINESSNAME ="" DATATYPE ="varchar2" DESCRIPTION ="" FIELDNUMBER ="3" KEYTYPE ="NOT A KEY" NAME ="GENDER" NULLABLE ="NULL" PICTURETEXT ="" PRECISION ="6" SCALE ="0"/>
        <TARGETFIELD BUSINESSNAME ="" DATATYPE ="date" DESCRIPTION ="" FIELDNUMBER ="4" KEYTYPE ="NOT A KEY" NAME ="DOB" NULLABLE ="NULL" PICTURETEXT ="" PRECISION ="19" SCALE ="0"/>
        <TARGETFIELD BUSINESSNAME ="" DATATYPE ="varchar2" DESCRIPTION ="" FIELDNUMBER ="5" KEYTYPE ="NOT A KEY" NAME ="CURRENT_MARRTIAL_STATUS" NULLABLE ="NULL" PICTURETEXT ="" PRECISION ="9" SCALE ="0"/>
        <TARGETFIELD BUSINESSNAME ="" DATATYPE ="varchar2" DESCRIPTION ="" FIELDNUMBER ="6" KEYTYPE ="NOT A KEY" NAME ="RELIGION" NULLABLE ="NULL" PICTURETEXT ="" PRECISION ="9" SCALE ="0"/>
        <TARGETFIELD BUSINESSNAME ="" DATATYPE ="varchar2" DESCRIPTION ="" FIELDNUMBER ="7" KEYTYPE ="NOT A KEY" NAME ="CASTE" NULLABLE ="NULL" PICTURETEXT ="" PRECISION ="5" SCALE ="0"/>
        <TARGETFIELD BUSINESSNAME ="" DATATYPE ="varchar2" DESCRIPTION ="" FIELDNUMBER ="8" KEYTYPE ="NOT A KEY" NAME ="DISABILITY" NULLABLE ="NULL" PICTURETEXT ="" PRECISION ="3" SCALE ="0"/>
        <TARGETFIELD BUSINESSNAME ="" DATATYPE ="varchar2" DESCRIPTION ="" FIELDNUMBER ="9" KEYTYPE ="NOT A KEY" NAME ="TYPE_OF_DISABILITY" NULLABLE ="NULL" PICTURETEXT ="" PRECISION ="19" SCALE ="0"/>
        <TARGETFIELD BUSINESSNAME ="" DATATYPE ="varchar2" DESCRIPTION ="" FIELDNUMBER ="10" KEYTYPE ="NOT A KEY" NAME ="LITERACY_STATUS" NULLABLE ="NULL" PICTURETEXT ="" PRECISION ="10" SCALE ="0"/>
        <TARGETFIELD BUSINESSNAME ="" DATATYPE ="varchar2" DESCRIPTION ="" FIELDNUMBER ="11" KEYTYPE ="NOT A KEY" NAME ="STATUS_OF_ATTENDANCE" NULLABLE ="NULL" PICTURETEXT ="" PRECISION ="10" SCALE ="0"/>
        <TARGETFIELD BUSINESSNAME ="" DATATYPE ="varchar2" DESCRIPTION ="" FIELDNUMBER ="12" KEYTYPE ="NOT A KEY" NAME ="HIGHEST_EDUCATION_LEVEL" NULLABLE ="NULL" PICTURETEXT ="" PRECISION ="3" SCALE ="0"/>
        <TARGETFIELD BUSINESSNAME ="" DATATYPE ="varchar2" DESCRIPTION ="" FIELDNUMBER ="13" KEYTYPE ="NOT A KEY" NAME ="OCCUPATION" NULLABLE ="NULL" PICTURETEXT ="" PRECISION ="17" SCALE ="0"/>
        <TARGETFIELD BUSINESSNAME ="" DATATYPE ="varchar2" DESCRIPTION ="" FIELDNUMBER ="14" KEYTYPE ="NOT A KEY" NAME ="NATURE_OF_INDUSTRY" NULLABLE ="NULL" PICTURETEXT ="" PRECISION ="19" SCALE ="0"/>
        <TARGETFIELD BUSINESSNAME ="" DATATYPE ="varchar2" DESCRIPTION ="" FIELDNUMBER ="15" KEYTYPE ="NOT A KEY" NAME ="SECTOR" NULLABLE ="NULL" PICTURETEXT ="" PRECISION ="13" SCALE ="0"/>
        <TARGETFIELD BUSINESSNAME ="" DATATYPE ="number(p,s)" DESCRIPTION ="" FIELDNUMBER ="16" KEYTYPE ="NOT A KEY" NAME ="SALARY" NULLABLE ="NULL" PICTURETEXT ="" PRECISION ="10" SCALE ="0"/>
        <TARGETFIELD BUSINESSNAME ="" DATATYPE ="varchar2" DESCRIPTION ="" FIELDNUMBER ="17" KEYTYPE ="NOT A KEY" NAME ="MODE_OF_TRAVELLING_TO_WORK" NULLABLE ="NULL" PICTURETEXT ="" PRECISION ="7" SCALE ="0"/>
        <TARGETFIELD BUSINESSNAME ="" DATATYPE ="varchar2" DESCRIPTION ="" FIELDNUMBER ="18" KEYTYPE ="NOT A KEY" NAME ="CHILDREN_SURVIVING" NULLABLE ="NULL" PICTURETEXT ="" PRECISION ="2" SCALE ="0"/>
        <TARGETFIELD BUSINESSNAME ="" DATATYPE ="varchar2" DESCRIPTION ="" FIELDNUMBER ="19" KEYTYPE ="NOT A KEY" NAME ="CHILDREN_EVER_BORN" NULLABLE ="NULL" PICTURETEXT ="" PRECISION ="2" SCALE ="0"/>
        <TARGETFIELD BUSINESSNAME ="" DATATYPE ="number(p,s)" DESCRIPTION ="" FIELDNUMBER ="20" KEYTYPE ="NOT A KEY" NAME ="NO_OF_PERSON_EXPIRED_IN_10_YRS" NULLABLE ="NULL" PICTURETEXT ="" PRECISION ="1" SCALE ="0"/>
        <TARGETFIELD BUSINESSNAME ="" DATATYPE ="varchar2" DESCRIPTION ="" FIELDNUMBER ="21" KEYTYPE ="NOT A KEY" NAME ="TYPE_OF_HOUSE" NULLABLE ="NULL" PICTURETEXT ="" PRECISION ="4" SCALE ="0"/>
        <TARGETFIELD BUSINESSNAME ="" DATATYPE ="varchar2" DESCRIPTION ="" FIELDNUMBER ="22" KEYTYPE ="NOT A KEY" NAME ="PAN_CARD" NULLABLE ="NULL" PICTURETEXT ="" PRECISION ="3" SCALE ="0"/>
        <TARGETFIELD BUSINESSNAME ="" DATATYPE ="varchar2" DESCRIPTION ="" FIELDNUMBER ="23" KEYTYPE ="NOT A KEY" NAME ="RATION_CARD" NULLABLE ="NULL" PICTURETEXT ="" PRECISION ="3" SCALE ="0"/>
        <TARGETFIELD BUSINESSNAME ="" DATATYPE ="varchar2" DESCRIPTION ="" FIELDNUMBER ="24" KEYTYPE ="NOT A KEY" NAME ="ADHAR_CARD" NULLABLE ="NULL" PICTURETEXT ="" PRECISION ="3" SCALE ="0"/>
        <TARGETFIELD BUSINESSNAME ="" DATATYPE ="varchar2" DESCRIPTION ="" FIELDNUMBER ="25" KEYTYPE ="NOT A KEY" NAME ="AREA" NULLABLE ="NULL" PICTURETEXT ="" PRECISION ="13" SCALE ="0"/>
        <TARGETFIELD BUSINESSNAME ="" DATATYPE ="varchar2" DESCRIPTION ="" FIELDNUMBER ="26" KEYTYPE ="NOT A KEY" NAME ="CITY" NULLABLE ="NULL" PICTURETEXT ="" PRECISION ="9" SCALE ="0"/>
    </TARGET>
    <MAPPING DESCRIPTION ="" ISVALID ="YES" NAME ="M_STG_CENSUS_LOAD1" OBJECTVERSION ="1" VERSIONNUMBER ="1">
        <TRANSFORMATION DESCRIPTION ="" NAME ="FILTRANS" OBJECTVERSION ="1" REUSABLE ="NO" TYPE ="Filter" VERSIONNUMBER ="1">
            <TRANSFORMFIELD DATATYPE ="string" DEFAULTVALUE ="" DESCRIPTION ="" NAME ="PERSON_ID" PICTURETEXT ="" PORTTYPE ="INPUT/OUTPUT" PRECISION ="4" SCALE ="0"/>
            <TRANSFORMFIELD DATATYPE ="decimal" DEFAULTVALUE ="" DESCRIPTION ="" NAME ="DOOR_NUMBER" PICTURETEXT ="" PORTTYPE ="INPUT/OUTPUT" PRECISION ="4" SCALE ="0"/>
            <TRANSFORMFIELD DATATYPE ="string" DEFAULTVALUE ="" DESCRIPTION ="" NAME ="GENDER" PICTURETEXT ="" PORTTYPE ="INPUT/OUTPUT" PRECISION ="6" SCALE ="0"/>
            <TRANSFORMFIELD DATATYPE ="date/time" DEFAULTVALUE ="" DESCRIPTION ="" NAME ="DOB_OP" PICTURETEXT ="" PORTTYPE ="INPUT/OUTPUT" PRECISION ="29" SCALE ="9"/>
            <TRANSFORMFIELD DATATYPE ="string" DEFAULTVALUE ="" DESCRIPTION ="" NAME ="CURRENT_MARRTIAL_STATUS" PICTURETEXT ="" PORTTYPE ="INPUT/OUTPUT" PRECISION ="9" SCALE ="0"/>
            <TRANSFORMFIELD DATATYPE ="string" DEFAULTVALUE ="" DESCRIPTION ="" NAME ="RELIGION" PICTURETEXT ="" PORTTYPE ="INPUT/OUTPUT" PRECISION ="9" SCALE ="0"/>
            <TRANSFORMFIELD DATATYPE ="string" DEFAULTVALUE ="" DESCRIPTION ="" NAME ="CASTE" PICTURETEXT ="" PORTTYPE ="INPUT/OUTPUT" PRECISION ="5" SCALE ="0"/>
            <TRANSFORMFIELD DATATYPE ="string" DEFAULTVALUE ="" DESCRIPTION ="" NAME ="DISABILITY" PICTURETEXT ="" PORTTYPE ="INPUT/OUTPUT" PRECISION ="3" SCALE ="0"/>
            <TRANSFORMFIELD DATATYPE ="string" DEFAULTVALUE ="" DESCRIPTION ="" NAME ="TYPE_OF_DISABILITY" PICTURETEXT ="" PORTTYPE ="INPUT/OUTPUT" PRECISION ="19" SCALE ="0"/>
            <TRANSFORMFIELD DATATYPE ="string" DEFAULTVALUE ="" DESCRIPTION ="" NAME ="LITERACY_STATUS" PICTURETEXT ="" PORTTYPE ="INPUT/OUTPUT" PRECISION ="10" SCALE ="0"/>
            <TRANSFORMFIELD DATATYPE ="string" DEFAULTVALUE ="" DESCRIPTION ="" NAME ="CURRENTSTATUS_OF_ATTENDANCE" PICTURETEXT ="" PORTTYPE ="INPUT/OUTPUT" PRECISION ="10" SCALE ="0"/>
            <TRANSFORMFIELD DATATYPE ="string" DEFAULTVALUE ="" DESCRIPTION ="" NAME ="HIGHEST_EDUCATION_LEVEL" PICTURETEXT ="" PORTTYPE ="INPUT/OUTPUT" PRECISION ="3" SCALE ="0"/>
            <TRANSFORMFIELD DATATYPE ="string" DEFAULTVALUE ="" DESCRIPTION ="" NAME ="OCCUPATION" PICTURETEXT ="" PORTTYPE ="INPUT/OUTPUT" PRECISION ="17" SCALE ="0"/>
            <TRANSFORMFIELD DATATYPE ="string" DEFAULTVALUE ="" DESCRIPTION ="" NAME ="NATURE_OF_INDUSTRY" PICTURETEXT ="" PORTTYPE ="INPUT/OUTPUT" PRECISION ="19" SCALE ="0"/>
            <TRANSFORMFIELD DATATYPE ="string" DEFAULTVALUE ="" DESCRIPTION ="" NAME ="SECTOR" PICTURETEXT ="" PORTTYPE ="INPUT/OUTPUT" PRECISION ="13" SCALE ="0"/>
            <TRANSFORMFIELD DATATYPE ="decimal" DEFAULTVALUE ="" DESCRIPTION ="" NAME ="SALARY" PICTURETEXT ="" PORTTYPE ="INPUT/OUTPUT" PRECISION ="10" SCALE ="0"/>
            <TRANSFORMFIELD DATATYPE ="string" DEFAULTVALUE ="" DESCRIPTION ="" NAME ="MODE_OF_TRAVELLING_TO_WORK_PLACE" PICTURETEXT ="" PORTTYPE ="INPUT/OUTPUT" PRECISION ="7" SCALE ="0"/>
            <TRANSFORMFIELD DATATYPE ="string" DEFAULTVALUE ="" DESCRIPTION ="" NAME ="CHILDREN_SURVIVING" PICTURETEXT ="" PORTTYPE ="INPUT/OUTPUT" PRECISION ="2" SCALE ="0"/>
            <TRANSFORMFIELD DATATYPE ="string" DEFAULTVALUE ="" DESCRIPTION ="" NAME ="CHILDREN_EVER_BORN" PICTURETEXT ="" PORTTYPE ="INPUT/OUTPUT" PRECISION ="2" SCALE ="0"/>
            <TRANSFORMFIELD DATATYPE ="decimal" DEFAULTVALUE ="" DESCRIPTION ="" NAME ="NUMBER_OF_PERSONS_EXPIRED_IN_LAST_10_YEARS" PICTURETEXT ="" PORTTYPE ="INPUT/OUTPUT" PRECISION ="1" SCALE ="0"/>
            <TRANSFORMFIELD DATATYPE ="string" DEFAULTVALUE ="" DESCRIPTION ="" NAME ="TYPE_OF_HOUSE" PICTURETEXT ="" PORTTYPE ="INPUT/OUTPUT" PRECISION ="4" SCALE ="0"/>
            <TRANSFORMFIELD DATATYPE ="string" DEFAULTVALUE ="" DESCRIPTION ="" NAME ="PAN_CARD" PICTURETEXT ="" PORTTYPE ="INPUT/OUTPUT" PRECISION ="3" SCALE ="0"/>
            <TRANSFORMFIELD DATATYPE ="string" DEFAULTVALUE ="" DESCRIPTION ="" NAME ="RATION_CARD" PICTURETEXT ="" PORTTYPE ="INPUT/OUTPUT" PRECISION ="3" SCALE ="0"/>
            <TRANSFORMFIELD DATATYPE ="string" DEFAULTVALUE ="" DESCRIPTION ="" NAME ="ADHAR_CARD" PICTURETEXT ="" PORTTYPE ="INPUT/OUTPUT" PRECISION ="3" SCALE ="0"/>
            <TRANSFORMFIELD DATATYPE ="string" DEFAULTVALUE ="" DESCRIPTION ="" NAME ="AREA" PICTURETEXT ="" PORTTYPE ="INPUT/OUTPUT" PRECISION ="13" SCALE ="0"/>
            <TRANSFORMFIELD DATATYPE ="string" DEFAULTVALUE ="" DESCRIPTION ="" NAME ="CITY" PICTURETEXT ="" PORTTYPE ="INPUT/OUTPUT" PRECISION ="9" SCALE ="0"/>
            <TABLEATTRIBUTE NAME ="Filter Condition" VALUE ="IIF(ISNULL(PERSON_ID),FALSE,TRUE)"/>
            <TABLEATTRIBUTE NAME ="Tracing Level" VALUE ="Normal"/>
        </TRANSFORMATION>
        <TRANSFORMATION DESCRIPTION ="" NAME ="SQ_Copy_of_Census_data" OBJECTVERSION ="1" REUSABLE ="NO" TYPE ="Source Qualifier" VERSIONNUMBER ="1">
            <TRANSFORMFIELD DATATYPE ="string" DEFAULTVALUE ="" DESCRIPTION ="" NAME ="PERSON_ID" PICTURETEXT ="" PORTTYPE ="INPUT/OUTPUT" PRECISION ="4" SCALE ="0"/>
            <TRANSFORMFIELD DATATYPE ="decimal" DEFAULTVALUE ="" DESCRIPTION ="" NAME ="DOOR_NUMBER" PICTURETEXT ="" PORTTYPE ="INPUT/OUTPUT" PRECISION ="4" SCALE ="0"/>
            <TRANSFORMFIELD DATATYPE ="string" DEFAULTVALUE ="" DESCRIPTION ="" NAME ="GENDER" PICTURETEXT ="" PORTTYPE ="INPUT/OUTPUT" PRECISION ="6" SCALE ="0"/>
            <TRANSFORMFIELD DATATYPE ="string" DEFAULTVALUE ="" DESCRIPTION ="" NAME ="DOB" PICTURETEXT ="" PORTTYPE ="INPUT/OUTPUT" PRECISION ="12" SCALE ="0"/>
            <TRANSFORMFIELD DATATYPE ="string" DEFAULTVALUE ="" DESCRIPTION ="" NAME ="CURRENT_MARRTIAL_STATUS" PICTURETEXT ="" PORTTYPE ="INPUT/OUTPUT" PRECISION ="9" SCALE ="0"/>
            <TRANSFORMFIELD DATATYPE ="string" DEFAULTVALUE ="" DESCRIPTION ="" NAME ="RELIGION" PICTURETEXT ="" PORTTYPE ="INPUT/OUTPUT" PRECISION ="9" SCALE ="0"/>
            <TRANSFORMFIELD DATATYPE ="string" DEFAULTVALUE ="" DESCRIPTION ="" NAME ="CASTE" PICTURETEXT ="" PORTTYPE ="INPUT/OUTPUT" PRECISION ="5" SCALE ="0"/>
            <TRANSFORMFIELD DATATYPE ="string" DEFAULTVALUE ="" DESCRIPTION ="" NAME ="DISABILITY" PICTURETEXT ="" PORTTYPE ="INPUT/OUTPUT" PRECISION ="3" SCALE ="0"/>
            <TRANSFORMFIELD DATATYPE ="string" DEFAULTVALUE ="" DESCRIPTION ="" NAME ="TYPE_OF_DISABILITY" PICTURETEXT ="" PORTTYPE ="INPUT/OUTPUT" PRECISION ="19" SCALE ="0"/>
            <TRANSFORMFIELD DATATYPE ="string" DEFAULTVALUE ="" DESCRIPTION ="" NAME ="LITERACY_STATUS" PICTURETEXT ="" PORTTYPE ="INPUT/OUTPUT" PRECISION ="10" SCALE ="0"/>
            <TRANSFORMFIELD DATATYPE ="string" DEFAULTVALUE ="" DESCRIPTION ="" NAME ="CURRENTSTATUS_OF_ATTENDANCE" PICTURETEXT ="" PORTTYPE ="INPUT/OUTPUT" PRECISION ="10" SCALE ="0"/>
            <TRANSFORMFIELD DATATYPE ="string" DEFAULTVALUE ="" DESCRIPTION ="" NAME ="HIGHEST_EDUCATION_LEVEL" PICTURETEXT ="" PORTTYPE ="INPUT/OUTPUT" PRECISION ="3" SCALE ="0"/>
            <TRANSFORMFIELD DATATYPE ="string" DEFAULTVALUE ="" DESCRIPTION ="" NAME ="OCCUPATION" PICTURETEXT ="" PORTTYPE ="INPUT/OUTPUT" PRECISION ="17" SCALE ="0"/>
            <TRANSFORMFIELD DATATYPE ="string" DEFAULTVALUE ="" DESCRIPTION ="" NAME ="NATURE_OF_INDUSTRY" PICTURETEXT ="" PORTTYPE ="INPUT/OUTPUT" PRECISION ="19" SCALE ="0"/>
            <TRANSFORMFIELD DATATYPE ="string" DEFAULTVALUE ="" DESCRIPTION ="" NAME ="SECTOR" PICTURETEXT ="" PORTTYPE ="INPUT/OUTPUT" PRECISION ="13" SCALE ="0"/>
            <TRANSFORMFIELD DATATYPE ="decimal" DEFAULTVALUE ="" DESCRIPTION ="" NAME ="SALARY" PICTURETEXT ="" PORTTYPE ="INPUT/OUTPUT" PRECISION ="10" SCALE ="0"/>
            <TRANSFORMFIELD DATATYPE ="string" DEFAULTVALUE ="" DESCRIPTION ="" NAME ="MODE_OF_TRAVELLING_TO_WORK_PLACE" PICTURETEXT ="" PORTTYPE ="INPUT/OUTPUT" PRECISION ="7" SCALE ="0"/>
            <TRANSFORMFIELD DATATYPE ="string" DEFAULTVALUE ="" DESCRIPTION ="" NAME ="CHILDREN_SURVIVING" PICTURETEXT ="" PORTTYPE ="INPUT/OUTPUT" PRECISION ="2" SCALE ="0"/>
            <TRANSFORMFIELD DATATYPE ="string" DEFAULTVALUE ="" DESCRIPTION ="" NAME ="CHILDREN_EVER_BORN" PICTURETEXT ="" PORTTYPE ="INPUT/OUTPUT" PRECISION ="2" SCALE ="0"/>
            <TRANSFORMFIELD DATATYPE ="decimal" DEFAULTVALUE ="" DESCRIPTION ="" NAME ="NUMBER_OF_PERSONS_EXPIRED_IN_LAST_10_YEARS" PICTURETEXT ="" PORTTYPE ="INPUT/OUTPUT" PRECISION ="1" SCALE ="0"/>
            <TRANSFORMFIELD DATATYPE ="string" DEFAULTVALUE ="" DESCRIPTION ="" NAME ="TYPE_OF_HOUSE" PICTURETEXT ="" PORTTYPE ="INPUT/OUTPUT" PRECISION ="4" SCALE ="0"/>
            <TRANSFORMFIELD DATATYPE ="string" DEFAULTVALUE ="" DESCRIPTION ="" NAME ="PAN_CARD" PICTURETEXT ="" PORTTYPE ="INPUT/OUTPUT" PRECISION ="3" SCALE ="0"/>
            <TRANSFORMFIELD DATATYPE ="string" DEFAULTVALUE ="" DESCRIPTION ="" NAME ="RATION_CARD" PICTURETEXT ="" PORTTYPE ="INPUT/OUTPUT" PRECISION ="3" SCALE ="0"/>
            <TRANSFORMFIELD DATATYPE ="string" DEFAULTVALUE ="" DESCRIPTION ="" NAME ="ADHAR_CARD" PICTURETEXT ="" PORTTYPE ="INPUT/OUTPUT" PRECISION ="3" SCALE ="0"/>
            <TRANSFORMFIELD DATATYPE ="string" DEFAULTVALUE ="" DESCRIPTION ="" NAME ="AREA" PICTURETEXT ="" PORTTYPE ="INPUT/OUTPUT" PRECISION ="13" SCALE ="0"/>
            <TRANSFORMFIELD DATATYPE ="string" DEFAULTVALUE ="" DESCRIPTION ="" NAME ="CITY" PICTURETEXT ="" PORTTYPE ="INPUT/OUTPUT" PRECISION ="9" SCALE ="0"/>
            <TABLEATTRIBUTE NAME ="Sql Query" VALUE =""/>
            <TABLEATTRIBUTE NAME ="User Defined Join" VALUE =""/>
            <TABLEATTRIBUTE NAME ="Source Filter" VALUE =""/>
            <TABLEATTRIBUTE NAME ="Number Of Sorted Ports" VALUE ="0"/>
            <TABLEATTRIBUTE NAME ="Tracing Level" VALUE ="Normal"/>
            <TABLEATTRIBUTE NAME ="Select Distinct" VALUE ="NO"/>
            <TABLEATTRIBUTE NAME ="Is Partitionable" VALUE ="NO"/>
            <TABLEATTRIBUTE NAME ="Pre SQL" VALUE =""/>
            <TABLEATTRIBUTE NAME ="Post SQL" VALUE =""/>
            <TABLEATTRIBUTE NAME ="Output is deterministic" VALUE ="NO"/>
            <TABLEATTRIBUTE NAME ="Output is repeatable" VALUE ="Never"/>
        </TRANSFORMATION>
        <TRANSFORMATION DESCRIPTION ="" NAME ="EXPTRANS" OBJECTVERSION ="1" REUSABLE ="NO" TYPE ="Expression" VERSIONNUMBER ="1">
            <TRANSFORMFIELD DATATYPE ="string" DEFAULTVALUE ="" DESCRIPTION ="" EXPRESSION ="PERSON_ID" EXPRESSIONTYPE ="GENERAL" NAME ="PERSON_ID" PICTURETEXT ="" PORTTYPE ="INPUT/OUTPUT" PRECISION ="4" SCALE ="0"/>
            <TRANSFORMFIELD DATATYPE ="decimal" DEFAULTVALUE ="" DESCRIPTION ="" EXPRESSION ="DOOR_NUMBER" EXPRESSIONTYPE ="GENERAL" NAME ="DOOR_NUMBER" PICTURETEXT ="" PORTTYPE ="INPUT/OUTPUT" PRECISION ="4" SCALE ="0"/>
            <TRANSFORMFIELD DATATYPE ="string" DEFAULTVALUE ="" DESCRIPTION ="" EXPRESSION ="GENDER" EXPRESSIONTYPE ="GENERAL" NAME ="GENDER" PICTURETEXT ="" PORTTYPE ="INPUT/OUTPUT" PRECISION ="6" SCALE ="0"/>
            <TRANSFORMFIELD DATATYPE ="string" DEFAULTVALUE ="" DESCRIPTION ="" NAME ="DOB" PICTURETEXT ="" PORTTYPE ="INPUT" PRECISION ="12" SCALE ="0"/>
            <TRANSFORMFIELD DATATYPE ="string" DEFAULTVALUE ="" DESCRIPTION ="" EXPRESSION ="LTRIM(RTRIM(DOB))" EXPRESSIONTYPE ="GENERAL" NAME ="DATE_TRIMED" PICTURETEXT ="" PORTTYPE ="LOCAL VARIABLE" PRECISION ="10" SCALE ="0"/>
            <TRANSFORMFIELD DATATYPE ="date/time" DEFAULTVALUE ="" DESCRIPTION ="" EXPRESSION ="IIF(IS_DATE(DATE_TRIMED, &apos;dd-mm-yyyy&apos;),&#xD;&#xA;&#x9;&#xD;&#xA;&#x9;to_date(DATE_TRIMED, &apos;dd/mm/yyyy&apos;),&#xD;&#xA;&#x9;&#x9;(IIF(IS_DATE(DATE_TRIMED, &apos;dd/mm/yyyy&apos;),&#xD;&#xA;&#x9;&#x9;&#x9;&#xD;&#xA;&#x9;&#x9;&#x9;to_date(DATE_TRIMED, &apos;mm/dd/yyyy&apos;), &#xD;&#xA;&#x9;&#x9;&#x9;&#x9;(IIF(IS_DATE(DATE_TRIMED, &apos;mm-dd-yyyy&apos;),&#xD;&#xA;&#x9;&#x9;&#x9;&#x9;&#x9;&#xD;&#xA;&#x9;&#x9;&#x9;&#x9;&#x9;to_date(DATE_TRIMED, &apos;mm/dd/yyyy&apos;))))))" EXPRESSIONTYPE ="GENERAL" NAME ="Conv_DOB" PICTURETEXT ="" PORTTYPE ="LOCAL VARIABLE" PRECISION ="29" SCALE ="9"/>
            <TRANSFORMFIELD DATATYPE ="string" DEFAULTVALUE ="" DESCRIPTION ="" EXPRESSION ="TO_CHAR(Conv_DOB)" EXPRESSIONTYPE ="GENERAL" NAME ="DOB_IP" PICTURETEXT ="" PORTTYPE ="LOCAL VARIABLE" PRECISION ="10" SCALE ="0"/>
            <TRANSFORMFIELD DATATYPE ="string" DEFAULTVALUE ="" DESCRIPTION ="" EXPRESSION ="DECODE(ISNULL(DOB_IP),1,&apos;08/14/1996&apos;,DOB_IP)" EXPRESSIONTYPE ="GENERAL" NAME ="DOB_DECODE" PICTURETEXT ="" PORTTYPE ="LOCAL VARIABLE" PRECISION ="10" SCALE ="0"/>
            <TRANSFORMFIELD DATATYPE ="date/time" DEFAULTVALUE ="ERROR(&apos;transformation error&apos;)" DESCRIPTION ="" EXPRESSION ="IIF(IS_DATE(DOB_DECODE, &apos;dd-mm-yyyy&apos;),&#xD;&#xA;&#x9;&#xD;&#xA;&#x9;to_date(DOB_DECODE, &apos;dd/mm/yyyy&apos;),&#xD;&#xA;&#x9;&#x9;(IIF(IS_DATE(DOB_DECODE, &apos;dd/mm/yyyy&apos;),&#xD;&#xA;&#x9;&#x9;&#x9;&#xD;&#xA;&#x9;&#x9;&#x9;to_date(DOB_DECODE, &apos;mm/dd/yyyy&apos;), &#xD;&#xA;&#x9;&#x9;&#x9;&#x9;(IIF(IS_DATE(DOB_DECODE, &apos;mm-dd-yyyy&apos;),&#xD;&#xA;&#x9;&#x9;&#x9;&#x9;&#x9;&#xD;&#xA;&#x9;&#x9;&#x9;&#x9;&#x9;to_date(DOB_DECODE, &apos;mm/dd/yyyy&apos;))))))" EXPRESSIONTYPE ="GENERAL" NAME ="DOB_OP" PICTURETEXT ="" PORTTYPE ="OUTPUT" PRECISION ="29" SCALE ="9"/>
            <TRANSFORMFIELD DATATYPE ="string" DEFAULTVALUE ="" DESCRIPTION ="" EXPRESSION ="CURRENT_MARRTIAL_STATUS" EXPRESSIONTYPE ="GENERAL" NAME ="CURRENT_MARRTIAL_STATUS" PICTURETEXT ="" PORTTYPE ="INPUT/OUTPUT" PRECISION ="9" SCALE ="0"/>
            <TRANSFORMFIELD DATATYPE ="string" DEFAULTVALUE ="" DESCRIPTION ="" EXPRESSION ="RELIGION" EXPRESSIONTYPE ="GENERAL" NAME ="RELIGION" PICTURETEXT ="" PORTTYPE ="INPUT/OUTPUT" PRECISION ="9" SCALE ="0"/>
            <TRANSFORMFIELD DATATYPE ="string" DEFAULTVALUE ="" DESCRIPTION ="" EXPRESSION ="CASTE" EXPRESSIONTYPE ="GENERAL" NAME ="CASTE" PICTURETEXT ="" PORTTYPE ="INPUT/OUTPUT" PRECISION ="5" SCALE ="0"/>
            <TRANSFORMFIELD DATATYPE ="string" DEFAULTVALUE ="" DESCRIPTION ="" EXPRESSION ="DISABILITY" EXPRESSIONTYPE ="GENERAL" NAME ="DISABILITY" PICTURETEXT ="" PORTTYPE ="INPUT/OUTPUT" PRECISION ="3" SCALE ="0"/>
            <TRANSFORMFIELD DATATYPE ="string" DEFAULTVALUE ="" DESCRIPTION ="" EXPRESSION ="TYPE_OF_DISABILITY" EXPRESSIONTYPE ="GENERAL" NAME ="TYPE_OF_DISABILITY" PICTURETEXT ="" PORTTYPE ="INPUT/OUTPUT" PRECISION ="19" SCALE ="0"/>
            <TRANSFORMFIELD DATATYPE ="string" DEFAULTVALUE ="" DESCRIPTION ="" EXPRESSION ="LITERACY_STATUS" EXPRESSIONTYPE ="GENERAL" NAME ="LITERACY_STATUS" PICTURETEXT ="" PORTTYPE ="INPUT/OUTPUT" PRECISION ="10" SCALE ="0"/>
            <TRANSFORMFIELD DATATYPE ="string" DEFAULTVALUE ="" DESCRIPTION ="" EXPRESSION ="CURRENTSTATUS_OF_ATTENDANCE" EXPRESSIONTYPE ="GENERAL" NAME ="CURRENTSTATUS_OF_ATTENDANCE" PICTURETEXT ="" PORTTYPE ="INPUT/OUTPUT" PRECISION ="10" SCALE ="0"/>
            <TRANSFORMFIELD DATATYPE ="string" DEFAULTVALUE ="" DESCRIPTION ="" EXPRESSION ="HIGHEST_EDUCATION_LEVEL" EXPRESSIONTYPE ="GENERAL" NAME ="HIGHEST_EDUCATION_LEVEL" PICTURETEXT ="" PORTTYPE ="INPUT/OUTPUT" PRECISION ="3" SCALE ="0"/>
            <TRANSFORMFIELD DATATYPE ="string" DEFAULTVALUE ="" DESCRIPTION ="" EXPRESSION ="OCCUPATION" EXPRESSIONTYPE ="GENERAL" NAME ="OCCUPATION" PICTURETEXT ="" PORTTYPE ="INPUT/OUTPUT" PRECISION ="17" SCALE ="0"/>
            <TRANSFORMFIELD DATATYPE ="string" DEFAULTVALUE ="" DESCRIPTION ="" EXPRESSION ="DECODE (OCCUPATION,&apos;PROFFESSOR&apos;,&apos;PROFESSOR&apos;,OCCUPATION)" EXPRESSIONTYPE ="GENERAL" NAME ="V_OCCUPATION" PICTURETEXT ="" PORTTYPE ="LOCAL VARIABLE" PRECISION ="20" SCALE ="0"/>
            <TRANSFORMFIELD DATATYPE ="string" DEFAULTVALUE ="ERROR(&apos;transformation error&apos;)" DESCRIPTION ="" EXPRESSION ="V_OCCUPATION" EXPRESSIONTYPE ="GENERAL" NAME ="O_OCCUPATION" PICTURETEXT ="" PORTTYPE ="OUTPUT" PRECISION ="20" SCALE ="0"/>
            <TRANSFORMFIELD DATATYPE ="string" DEFAULTVALUE ="" DESCRIPTION ="" EXPRESSION ="NATURE_OF_INDUSTRY" EXPRESSIONTYPE ="GENERAL" NAME ="NATURE_OF_INDUSTRY" PICTURETEXT ="" PORTTYPE ="INPUT/OUTPUT" PRECISION ="19" SCALE ="0"/>
            <TRANSFORMFIELD DATATYPE ="string" DEFAULTVALUE ="" DESCRIPTION ="" EXPRESSION ="SECTOR" EXPRESSIONTYPE ="GENERAL" NAME ="SECTOR" PICTURETEXT ="" PORTTYPE ="INPUT/OUTPUT" PRECISION ="13" SCALE ="0"/>
            <TRANSFORMFIELD DATATYPE ="decimal" DEFAULTVALUE ="" DESCRIPTION ="" EXPRESSION ="SALARY" EXPRESSIONTYPE ="GENERAL" NAME ="SALARY" PICTURETEXT ="" PORTTYPE ="INPUT/OUTPUT" PRECISION ="10" SCALE ="0"/>
            <TRANSFORMFIELD DATATYPE ="string" DEFAULTVALUE ="" DESCRIPTION ="" EXPRESSION ="MODE_OF_TRAVELLING_TO_WORK_PLACE" EXPRESSIONTYPE ="GENERAL" NAME ="MODE_OF_TRAVELLING_TO_WORK_PLACE" PICTURETEXT ="" PORTTYPE ="INPUT/OUTPUT" PRECISION ="7" SCALE ="0"/>
            <TRANSFORMFIELD DATATYPE ="string" DEFAULTVALUE ="" DESCRIPTION ="" EXPRESSION ="CHILDREN_SURVIVING" EXPRESSIONTYPE ="GENERAL" NAME ="CHILDREN_SURVIVING" PICTURETEXT ="" PORTTYPE ="INPUT/OUTPUT" PRECISION ="2" SCALE ="0"/>
            <TRANSFORMFIELD DATATYPE ="string" DEFAULTVALUE ="" DESCRIPTION ="" EXPRESSION ="CHILDREN_EVER_BORN" EXPRESSIONTYPE ="GENERAL" NAME ="CHILDREN_EVER_BORN" PICTURETEXT ="" PORTTYPE ="INPUT/OUTPUT" PRECISION ="2" SCALE ="0"/>
            <TRANSFORMFIELD DATATYPE ="decimal" DEFAULTVALUE ="" DESCRIPTION ="" EXPRESSION ="NUMBER_OF_PERSONS_EXPIRED_IN_LAST_10_YEARS" EXPRESSIONTYPE ="GENERAL" NAME ="NUMBER_OF_PERSONS_EXPIRED_IN_LAST_10_YEARS" PICTURETEXT ="" PORTTYPE ="INPUT/OUTPUT" PRECISION ="1" SCALE ="0"/>
            <TRANSFORMFIELD DATATYPE ="string" DEFAULTVALUE ="" DESCRIPTION ="" EXPRESSION ="TYPE_OF_HOUSE" EXPRESSIONTYPE ="GENERAL" NAME ="TYPE_OF_HOUSE" PICTURETEXT ="" PORTTYPE ="INPUT/OUTPUT" PRECISION ="4" SCALE ="0"/>
            <TRANSFORMFIELD DATATYPE ="string" DEFAULTVALUE ="" DESCRIPTION ="" EXPRESSION ="PAN_CARD" EXPRESSIONTYPE ="GENERAL" NAME ="PAN_CARD" PICTURETEXT ="" PORTTYPE ="INPUT/OUTPUT" PRECISION ="3" SCALE ="0"/>
            <TRANSFORMFIELD DATATYPE ="string" DEFAULTVALUE ="" DESCRIPTION ="" EXPRESSION ="RATION_CARD" EXPRESSIONTYPE ="GENERAL" NAME ="RATION_CARD" PICTURETEXT ="" PORTTYPE ="INPUT/OUTPUT" PRECISION ="3" SCALE ="0"/>
            <TRANSFORMFIELD DATATYPE ="string" DEFAULTVALUE ="" DESCRIPTION ="" EXPRESSION ="ADHAR_CARD" EXPRESSIONTYPE ="GENERAL" NAME ="ADHAR_CARD" PICTURETEXT ="" PORTTYPE ="INPUT/OUTPUT" PRECISION ="3" SCALE ="0"/>
            <TRANSFORMFIELD DATATYPE ="string" DEFAULTVALUE ="" DESCRIPTION ="" EXPRESSION ="AREA" EXPRESSIONTYPE ="GENERAL" NAME ="AREA" PICTURETEXT ="" PORTTYPE ="INPUT/OUTPUT" PRECISION ="13" SCALE ="0"/>
            <TRANSFORMFIELD DATATYPE ="string" DEFAULTVALUE ="" DESCRIPTION ="" EXPRESSION ="CITY" EXPRESSIONTYPE ="GENERAL" NAME ="CITY" PICTURETEXT ="" PORTTYPE ="INPUT/OUTPUT" PRECISION ="9" SCALE ="0"/>
            <TABLEATTRIBUTE NAME ="Tracing Level" VALUE ="Normal"/>
        </TRANSFORMATION>
        <INSTANCE DESCRIPTION ="" NAME ="CENSUS_DATA_TGT_STG" TRANSFORMATION_NAME ="CENSUS_DATA_TGT_STG" TRANSFORMATION_TYPE ="Target Definition" TYPE ="TARGET"/>
        <INSTANCE DESCRIPTION ="" NAME ="FILTRANS" REUSABLE ="NO" TRANSFORMATION_NAME ="FILTRANS" TRANSFORMATION_TYPE ="Filter" TYPE ="TRANSFORMATION"/>
        <INSTANCE DBDNAME ="FlatFile" DESCRIPTION ="" NAME ="Copy_of_Census_data" TRANSFORMATION_NAME ="Copy_of_Census_data" TRANSFORMATION_TYPE ="Source Definition" TYPE ="SOURCE"/>
        <INSTANCE DESCRIPTION ="" NAME ="SQ_Copy_of_Census_data" REUSABLE ="NO" TRANSFORMATION_NAME ="SQ_Copy_of_Census_data" TRANSFORMATION_TYPE ="Source Qualifier" TYPE ="TRANSFORMATION">
            <ASSOCIATED_SOURCE_INSTANCE NAME ="Copy_of_Census_data"/>
        </INSTANCE>
        <INSTANCE DESCRIPTION ="" NAME ="EXPTRANS" REUSABLE ="NO" TRANSFORMATION_NAME ="EXPTRANS" TRANSFORMATION_TYPE ="Expression" TYPE ="TRANSFORMATION"/>
        <CONNECTOR FROMFIELD ="RATION_CARD" FROMINSTANCE ="FILTRANS" FROMINSTANCETYPE ="Filter" TOFIELD ="RATION_CARD" TOINSTANCE ="CENSUS_DATA_TGT_STG" TOINSTANCETYPE ="Target Definition"/>
        <CONNECTOR FROMFIELD ="ADHAR_CARD" FROMINSTANCE ="FILTRANS" FROMINSTANCETYPE ="Filter" TOFIELD ="ADHAR_CARD" TOINSTANCE ="CENSUS_DATA_TGT_STG" TOINSTANCETYPE ="Target Definition"/>
        <CONNECTOR FROMFIELD ="AREA" FROMINSTANCE ="FILTRANS" FROMINSTANCETYPE ="Filter" TOFIELD ="AREA" TOINSTANCE ="CENSUS_DATA_TGT_STG" TOINSTANCETYPE ="Target Definition"/>
        <CONNECTOR FROMFIELD ="CITY" FROMINSTANCE ="FILTRANS" FROMINSTANCETYPE ="Filter" TOFIELD ="CITY" TOINSTANCE ="CENSUS_DATA_TGT_STG" TOINSTANCETYPE ="Target Definition"/>
        <CONNECTOR FROMFIELD ="PERSON_ID" FROMINSTANCE ="FILTRANS" FROMINSTANCETYPE ="Filter" TOFIELD ="PERSON_ID" TOINSTANCE ="CENSUS_DATA_TGT_STG" TOINSTANCETYPE ="Target Definition"/>
        <CONNECTOR FROMFIELD ="DOOR_NUMBER" FROMINSTANCE ="FILTRANS" FROMINSTANCETYPE ="Filter" TOFIELD ="DOOR_NUMBER" TOINSTANCE ="CENSUS_DATA_TGT_STG" TOINSTANCETYPE ="Target Definition"/>
        <CONNECTOR FROMFIELD ="GENDER" FROMINSTANCE ="FILTRANS" FROMINSTANCETYPE ="Filter" TOFIELD ="GENDER" TOINSTANCE ="CENSUS_DATA_TGT_STG" TOINSTANCETYPE ="Target Definition"/>
        <CONNECTOR FROMFIELD ="DOB_OP" FROMINSTANCE ="FILTRANS" FROMINSTANCETYPE ="Filter" TOFIELD ="DOB" TOINSTANCE ="CENSUS_DATA_TGT_STG" TOINSTANCETYPE ="Target Definition"/>
        <CONNECTOR FROMFIELD ="CURRENT_MARRTIAL_STATUS" FROMINSTANCE ="FILTRANS" FROMINSTANCETYPE ="Filter" TOFIELD ="CURRENT_MARRTIAL_STATUS" TOINSTANCE ="CENSUS_DATA_TGT_STG" TOINSTANCETYPE ="Target Definition"/>
        <CONNECTOR FROMFIELD ="RELIGION" FROMINSTANCE ="FILTRANS" FROMINSTANCETYPE ="Filter" TOFIELD ="RELIGION" TOINSTANCE ="CENSUS_DATA_TGT_STG" TOINSTANCETYPE ="Target Definition"/>
        <CONNECTOR FROMFIELD ="CASTE" FROMINSTANCE ="FILTRANS" FROMINSTANCETYPE ="Filter" TOFIELD ="CASTE" TOINSTANCE ="CENSUS_DATA_TGT_STG" TOINSTANCETYPE ="Target Definition"/>
        <CONNECTOR FROMFIELD ="DISABILITY" FROMINSTANCE ="FILTRANS" FROMINSTANCETYPE ="Filter" TOFIELD ="DISABILITY" TOINSTANCE ="CENSUS_DATA_TGT_STG" TOINSTANCETYPE ="Target Definition"/>
        <CONNECTOR FROMFIELD ="TYPE_OF_DISABILITY" FROMINSTANCE ="FILTRANS" FROMINSTANCETYPE ="Filter" TOFIELD ="TYPE_OF_DISABILITY" TOINSTANCE ="CENSUS_DATA_TGT_STG" TOINSTANCETYPE ="Target Definition"/>
        <CONNECTOR FROMFIELD ="LITERACY_STATUS" FROMINSTANCE ="FILTRANS" FROMINSTANCETYPE ="Filter" TOFIELD ="LITERACY_STATUS" TOINSTANCE ="CENSUS_DATA_TGT_STG" TOINSTANCETYPE ="Target Definition"/>
        <CONNECTOR FROMFIELD ="CURRENTSTATUS_OF_ATTENDANCE" FROMINSTANCE ="FILTRANS" FROMINSTANCETYPE ="Filter" TOFIELD ="STATUS_OF_ATTENDANCE" TOINSTANCE ="CENSUS_DATA_TGT_STG" TOINSTANCETYPE ="Target Definition"/>
        <CONNECTOR FROMFIELD ="HIGHEST_EDUCATION_LEVEL" FROMINSTANCE ="FILTRANS" FROMINSTANCETYPE ="Filter" TOFIELD ="HIGHEST_EDUCATION_LEVEL" TOINSTANCE ="CENSUS_DATA_TGT_STG" TOINSTANCETYPE ="Target Definition"/>
        <CONNECTOR FROMFIELD ="OCCUPATION" FROMINSTANCE ="FILTRANS" FROMINSTANCETYPE ="Filter" TOFIELD ="OCCUPATION" TOINSTANCE ="CENSUS_DATA_TGT_STG" TOINSTANCETYPE ="Target Definition"/>
        <CONNECTOR FROMFIELD ="NATURE_OF_INDUSTRY" FROMINSTANCE ="FILTRANS" FROMINSTANCETYPE ="Filter" TOFIELD ="NATURE_OF_INDUSTRY" TOINSTANCE ="CENSUS_DATA_TGT_STG" TOINSTANCETYPE ="Target Definition"/>
        <CONNECTOR FROMFIELD ="SECTOR" FROMINSTANCE ="FILTRANS" FROMINSTANCETYPE ="Filter" TOFIELD ="SECTOR" TOINSTANCE ="CENSUS_DATA_TGT_STG" TOINSTANCETYPE ="Target Definition"/>
        <CONNECTOR FROMFIELD ="SALARY" FROMINSTANCE ="FILTRANS" FROMINSTANCETYPE ="Filter" TOFIELD ="SALARY" TOINSTANCE ="CENSUS_DATA_TGT_STG" TOINSTANCETYPE ="Target Definition"/>
        <CONNECTOR FROMFIELD ="MODE_OF_TRAVELLING_TO_WORK_PLACE" FROMINSTANCE ="FILTRANS" FROMINSTANCETYPE ="Filter" TOFIELD ="MODE_OF_TRAVELLING_TO_WORK" TOINSTANCE ="CENSUS_DATA_TGT_STG" TOINSTANCETYPE ="Target Definition"/>
        <CONNECTOR FROMFIELD ="CHILDREN_SURVIVING" FROMINSTANCE ="FILTRANS" FROMINSTANCETYPE ="Filter" TOFIELD ="CHILDREN_SURVIVING" TOINSTANCE ="CENSUS_DATA_TGT_STG" TOINSTANCETYPE ="Target Definition"/>
        <CONNECTOR FROMFIELD ="CHILDREN_EVER_BORN" FROMINSTANCE ="FILTRANS" FROMINSTANCETYPE ="Filter" TOFIELD ="CHILDREN_EVER_BORN" TOINSTANCE ="CENSUS_DATA_TGT_STG" TOINSTANCETYPE ="Target Definition"/>
        <CONNECTOR FROMFIELD ="NUMBER_OF_PERSONS_EXPIRED_IN_LAST_10_YEARS" FROMINSTANCE ="FILTRANS" FROMINSTANCETYPE ="Filter" TOFIELD ="NO_OF_PERSON_EXPIRED_IN_10_YRS" TOINSTANCE ="CENSUS_DATA_TGT_STG" TOINSTANCETYPE ="Target Definition"/>
        <CONNECTOR FROMFIELD ="TYPE_OF_HOUSE" FROMINSTANCE ="FILTRANS" FROMINSTANCETYPE ="Filter" TOFIELD ="TYPE_OF_HOUSE" TOINSTANCE ="CENSUS_DATA_TGT_STG" TOINSTANCETYPE ="Target Definition"/>
        <CONNECTOR FROMFIELD ="PAN_CARD" FROMINSTANCE ="FILTRANS" FROMINSTANCETYPE ="Filter" TOFIELD ="PAN_CARD" TOINSTANCE ="CENSUS_DATA_TGT_STG" TOINSTANCETYPE ="Target Definition"/>
        <CONNECTOR FROMFIELD ="PERSON_ID" FROMINSTANCE ="EXPTRANS" FROMINSTANCETYPE ="Expression" TOFIELD ="PERSON_ID" TOINSTANCE ="FILTRANS" TOINSTANCETYPE ="Filter"/>
        <CONNECTOR FROMFIELD ="DOOR_NUMBER" FROMINSTANCE ="EXPTRANS" FROMINSTANCETYPE ="Expression" TOFIELD ="DOOR_NUMBER" TOINSTANCE ="FILTRANS" TOINSTANCETYPE ="Filter"/>
        <CONNECTOR FROMFIELD ="GENDER" FROMINSTANCE ="EXPTRANS" FROMINSTANCETYPE ="Expression" TOFIELD ="GENDER" TOINSTANCE ="FILTRANS" TOINSTANCETYPE ="Filter"/>
        <CONNECTOR FROMFIELD ="DOB_OP" FROMINSTANCE ="EXPTRANS" FROMINSTANCETYPE ="Expression" TOFIELD ="DOB_OP" TOINSTANCE ="FILTRANS" TOINSTANCETYPE ="Filter"/>
        <CONNECTOR FROMFIELD ="CURRENT_MARRTIAL_STATUS" FROMINSTANCE ="EXPTRANS" FROMINSTANCETYPE ="Expression" TOFIELD ="CURRENT_MARRTIAL_STATUS" TOINSTANCE ="FILTRANS" TOINSTANCETYPE ="Filter"/>
        <CONNECTOR FROMFIELD ="RELIGION" FROMINSTANCE ="EXPTRANS" FROMINSTANCETYPE ="Expression" TOFIELD ="RELIGION" TOINSTANCE ="FILTRANS" TOINSTANCETYPE ="Filter"/>
        <CONNECTOR FROMFIELD ="CASTE" FROMINSTANCE ="EXPTRANS" FROMINSTANCETYPE ="Expression" TOFIELD ="CASTE" TOINSTANCE ="FILTRANS" TOINSTANCETYPE ="Filter"/>
        <CONNECTOR FROMFIELD ="DISABILITY" FROMINSTANCE ="EXPTRANS" FROMINSTANCETYPE ="Expression" TOFIELD ="DISABILITY" TOINSTANCE ="FILTRANS" TOINSTANCETYPE ="Filter"/>
        <CONNECTOR FROMFIELD ="TYPE_OF_DISABILITY" FROMINSTANCE ="EXPTRANS" FROMINSTANCETYPE ="Expression" TOFIELD ="TYPE_OF_DISABILITY" TOINSTANCE ="FILTRANS" TOINSTANCETYPE ="Filter"/>
        <CONNECTOR FROMFIELD ="LITERACY_STATUS" FROMINSTANCE ="EXPTRANS" FROMINSTANCETYPE ="Expression" TOFIELD ="LITERACY_STATUS" TOINSTANCE ="FILTRANS" TOINSTANCETYPE ="Filter"/>
        <CONNECTOR FROMFIELD ="CURRENTSTATUS_OF_ATTENDANCE" FROMINSTANCE ="EXPTRANS" FROMINSTANCETYPE ="Expression" TOFIELD ="CURRENTSTATUS_OF_ATTENDANCE" TOINSTANCE ="FILTRANS" TOINSTANCETYPE ="Filter"/>
        <CONNECTOR FROMFIELD ="HIGHEST_EDUCATION_LEVEL" FROMINSTANCE ="EXPTRANS" FROMINSTANCETYPE ="Expression" TOFIELD ="HIGHEST_EDUCATION_LEVEL" TOINSTANCE ="FILTRANS" TOINSTANCETYPE ="Filter"/>
        <CONNECTOR FROMFIELD ="NATURE_OF_INDUSTRY" FROMINSTANCE ="EXPTRANS" FROMINSTANCETYPE ="Expression" TOFIELD ="NATURE_OF_INDUSTRY" TOINSTANCE ="FILTRANS" TOINSTANCETYPE ="Filter"/>
        <CONNECTOR FROMFIELD ="SECTOR" FROMINSTANCE ="EXPTRANS" FROMINSTANCETYPE ="Expression" TOFIELD ="SECTOR" TOINSTANCE ="FILTRANS" TOINSTANCETYPE ="Filter"/>
        <CONNECTOR FROMFIELD ="SALARY" FROMINSTANCE ="EXPTRANS" FROMINSTANCETYPE ="Expression" TOFIELD ="SALARY" TOINSTANCE ="FILTRANS" TOINSTANCETYPE ="Filter"/>
        <CONNECTOR FROMFIELD ="MODE_OF_TRAVELLING_TO_WORK_PLACE" FROMINSTANCE ="EXPTRANS" FROMINSTANCETYPE ="Expression" TOFIELD ="MODE_OF_TRAVELLING_TO_WORK_PLACE" TOINSTANCE ="FILTRANS" TOINSTANCETYPE ="Filter"/>
        <CONNECTOR FROMFIELD ="CHILDREN_SURVIVING" FROMINSTANCE ="EXPTRANS" FROMINSTANCETYPE ="Expression" TOFIELD ="CHILDREN_SURVIVING" TOINSTANCE ="FILTRANS" TOINSTANCETYPE ="Filter"/>
        <CONNECTOR FROMFIELD ="CHILDREN_EVER_BORN" FROMINSTANCE ="EXPTRANS" FROMINSTANCETYPE ="Expression" TOFIELD ="CHILDREN_EVER_BORN" TOINSTANCE ="FILTRANS" TOINSTANCETYPE ="Filter"/>
        <CONNECTOR FROMFIELD ="NUMBER_OF_PERSONS_EXPIRED_IN_LAST_10_YEARS" FROMINSTANCE ="EXPTRANS" FROMINSTANCETYPE ="Expression" TOFIELD ="NUMBER_OF_PERSONS_EXPIRED_IN_LAST_10_YEARS" TOINSTANCE ="FILTRANS" TOINSTANCETYPE ="Filter"/>
        <CONNECTOR FROMFIELD ="TYPE_OF_HOUSE" FROMINSTANCE ="EXPTRANS" FROMINSTANCETYPE ="Expression" TOFIELD ="TYPE_OF_HOUSE" TOINSTANCE ="FILTRANS" TOINSTANCETYPE ="Filter"/>
        <CONNECTOR FROMFIELD ="PAN_CARD" FROMINSTANCE ="EXPTRANS" FROMINSTANCETYPE ="Expression" TOFIELD ="PAN_CARD" TOINSTANCE ="FILTRANS" TOINSTANCETYPE ="Filter"/>
        <CONNECTOR FROMFIELD ="RATION_CARD" FROMINSTANCE ="EXPTRANS" FROMINSTANCETYPE ="Expression" TOFIELD ="RATION_CARD" TOINSTANCE ="FILTRANS" TOINSTANCETYPE ="Filter"/>
        <CONNECTOR FROMFIELD ="ADHAR_CARD" FROMINSTANCE ="EXPTRANS" FROMINSTANCETYPE ="Expression" TOFIELD ="ADHAR_CARD" TOINSTANCE ="FILTRANS" TOINSTANCETYPE ="Filter"/>
        <CONNECTOR FROMFIELD ="AREA" FROMINSTANCE ="EXPTRANS" FROMINSTANCETYPE ="Expression" TOFIELD ="AREA" TOINSTANCE ="FILTRANS" TOINSTANCETYPE ="Filter"/>
        <CONNECTOR FROMFIELD ="CITY" FROMINSTANCE ="EXPTRANS" FROMINSTANCETYPE ="Expression" TOFIELD ="CITY" TOINSTANCE ="FILTRANS" TOINSTANCETYPE ="Filter"/>
        <CONNECTOR FROMFIELD ="O_OCCUPATION" FROMINSTANCE ="EXPTRANS" FROMINSTANCETYPE ="Expression" TOFIELD ="OCCUPATION" TOINSTANCE ="FILTRANS" TOINSTANCETYPE ="Filter"/>
        <CONNECTOR FROMFIELD ="PERSON_ID" FROMINSTANCE ="Copy_of_Census_data" FROMINSTANCETYPE ="Source Definition" TOFIELD ="PERSON_ID" TOINSTANCE ="SQ_Copy_of_Census_data" TOINSTANCETYPE ="Source Qualifier"/>
        <CONNECTOR FROMFIELD ="DOOR_NUMBER" FROMINSTANCE ="Copy_of_Census_data" FROMINSTANCETYPE ="Source Definition" TOFIELD ="DOOR_NUMBER" TOINSTANCE ="SQ_Copy_of_Census_data" TOINSTANCETYPE ="Source Qualifier"/>
        <CONNECTOR FROMFIELD ="GENDER" FROMINSTANCE ="Copy_of_Census_data" FROMINSTANCETYPE ="Source Definition" TOFIELD ="GENDER" TOINSTANCE ="SQ_Copy_of_Census_data" TOINSTANCETYPE ="Source Qualifier"/>
        <CONNECTOR FROMFIELD ="DOB" FROMINSTANCE ="Copy_of_Census_data" FROMINSTANCETYPE ="Source Definition" TOFIELD ="DOB" TOINSTANCE ="SQ_Copy_of_Census_data" TOINSTANCETYPE ="Source Qualifier"/>
        <CONNECTOR FROMFIELD ="CURRENT_MARRTIAL_STATUS" FROMINSTANCE ="Copy_of_Census_data" FROMINSTANCETYPE ="Source Definition" TOFIELD ="CURRENT_MARRTIAL_STATUS" TOINSTANCE ="SQ_Copy_of_Census_data" TOINSTANCETYPE ="Source Qualifier"/>
        <CONNECTOR FROMFIELD ="RELIGION" FROMINSTANCE ="Copy_of_Census_data" FROMINSTANCETYPE ="Source Definition" TOFIELD ="RELIGION" TOINSTANCE ="SQ_Copy_of_Census_data" TOINSTANCETYPE ="Source Qualifier"/>
        <CONNECTOR FROMFIELD ="CASTE" FROMINSTANCE ="Copy_of_Census_data" FROMINSTANCETYPE ="Source Definition" TOFIELD ="CASTE" TOINSTANCE ="SQ_Copy_of_Census_data" TOINSTANCETYPE ="Source Qualifier"/>
        <CONNECTOR FROMFIELD ="DISABILITY" FROMINSTANCE ="Copy_of_Census_data" FROMINSTANCETYPE ="Source Definition" TOFIELD ="DISABILITY" TOINSTANCE ="SQ_Copy_of_Census_data" TOINSTANCETYPE ="Source Qualifier"/>
        <CONNECTOR FROMFIELD ="TYPE_OF_DISABILITY" FROMINSTANCE ="Copy_of_Census_data" FROMINSTANCETYPE ="Source Definition" TOFIELD ="TYPE_OF_DISABILITY" TOINSTANCE ="SQ_Copy_of_Census_data" TOINSTANCETYPE ="Source Qualifier"/>
        <CONNECTOR FROMFIELD ="LITERACY_STATUS" FROMINSTANCE ="Copy_of_Census_data" FROMINSTANCETYPE ="Source Definition" TOFIELD ="LITERACY_STATUS" TOINSTANCE ="SQ_Copy_of_Census_data" TOINSTANCETYPE ="Source Qualifier"/>
        <CONNECTOR FROMFIELD ="CURRENTSTATUS_OF_ATTENDANCE" FROMINSTANCE ="Copy_of_Census_data" FROMINSTANCETYPE ="Source Definition" TOFIELD ="CURRENTSTATUS_OF_ATTENDANCE" TOINSTANCE ="SQ_Copy_of_Census_data" TOINSTANCETYPE ="Source Qualifier"/>
        <CONNECTOR FROMFIELD ="HIGHEST_EDUCATION_LEVEL" FROMINSTANCE ="Copy_of_Census_data" FROMINSTANCETYPE ="Source Definition" TOFIELD ="HIGHEST_EDUCATION_LEVEL" TOINSTANCE ="SQ_Copy_of_Census_data" TOINSTANCETYPE ="Source Qualifier"/>
        <CONNECTOR FROMFIELD ="OCCUPATION" FROMINSTANCE ="Copy_of_Census_data" FROMINSTANCETYPE ="Source Definition" TOFIELD ="OCCUPATION" TOINSTANCE ="SQ_Copy_of_Census_data" TOINSTANCETYPE ="Source Qualifier"/>
        <CONNECTOR FROMFIELD ="NATURE_OF_INDUSTRY" FROMINSTANCE ="Copy_of_Census_data" FROMINSTANCETYPE ="Source Definition" TOFIELD ="NATURE_OF_INDUSTRY" TOINSTANCE ="SQ_Copy_of_Census_data" TOINSTANCETYPE ="Source Qualifier"/>
        <CONNECTOR FROMFIELD ="SECTOR" FROMINSTANCE ="Copy_of_Census_data" FROMINSTANCETYPE ="Source Definition" TOFIELD ="SECTOR" TOINSTANCE ="SQ_Copy_of_Census_data" TOINSTANCETYPE ="Source Qualifier"/>
        <CONNECTOR FROMFIELD ="SALARY" FROMINSTANCE ="Copy_of_Census_data" FROMINSTANCETYPE ="Source Definition" TOFIELD ="SALARY" TOINSTANCE ="SQ_Copy_of_Census_data" TOINSTANCETYPE ="Source Qualifier"/>
        <CONNECTOR FROMFIELD ="MODE_OF_TRAVELLING_TO_WORK_PLACE" FROMINSTANCE ="Copy_of_Census_data" FROMINSTANCETYPE ="Source Definition" TOFIELD ="MODE_OF_TRAVELLING_TO_WORK_PLACE" TOINSTANCE ="SQ_Copy_of_Census_data" TOINSTANCETYPE ="Source Qualifier"/>
        <CONNECTOR FROMFIELD ="CHILDREN_SURVIVING" FROMINSTANCE ="Copy_of_Census_data" FROMINSTANCETYPE ="Source Definition" TOFIELD ="CHILDREN_SURVIVING" TOINSTANCE ="SQ_Copy_of_Census_data" TOINSTANCETYPE ="Source Qualifier"/>
        <CONNECTOR FROMFIELD ="CHILDREN_EVER_BORN" FROMINSTANCE ="Copy_of_Census_data" FROMINSTANCETYPE ="Source Definition" TOFIELD ="CHILDREN_EVER_BORN" TOINSTANCE ="SQ_Copy_of_Census_data" TOINSTANCETYPE ="Source Qualifier"/>
        <CONNECTOR FROMFIELD ="NUMBER_OF_PERSONS_EXPIRED_IN_LAST_10_YEARS" FROMINSTANCE ="Copy_of_Census_data" FROMINSTANCETYPE ="Source Definition" TOFIELD ="NUMBER_OF_PERSONS_EXPIRED_IN_LAST_10_YEARS" TOINSTANCE ="SQ_Copy_of_Census_data" TOINSTANCETYPE ="Source Qualifier"/>
        <CONNECTOR FROMFIELD ="TYPE_OF_HOUSE" FROMINSTANCE ="Copy_of_Census_data" FROMINSTANCETYPE ="Source Definition" TOFIELD ="TYPE_OF_HOUSE" TOINSTANCE ="SQ_Copy_of_Census_data" TOINSTANCETYPE ="Source Qualifier"/>
        <CONNECTOR FROMFIELD ="PAN_CARD" FROMINSTANCE ="Copy_of_Census_data" FROMINSTANCETYPE ="Source Definition" TOFIELD ="PAN_CARD" TOINSTANCE ="SQ_Copy_of_Census_data" TOINSTANCETYPE ="Source Qualifier"/>
        <CONNECTOR FROMFIELD ="RATION_CARD" FROMINSTANCE ="Copy_of_Census_data" FROMINSTANCETYPE ="Source Definition" TOFIELD ="RATION_CARD" TOINSTANCE ="SQ_Copy_of_Census_data" TOINSTANCETYPE ="Source Qualifier"/>
        <CONNECTOR FROMFIELD ="ADHAR_CARD" FROMINSTANCE ="Copy_of_Census_data" FROMINSTANCETYPE ="Source Definition" TOFIELD ="ADHAR_CARD" TOINSTANCE ="SQ_Copy_of_Census_data" TOINSTANCETYPE ="Source Qualifier"/>
        <CONNECTOR FROMFIELD ="AREA" FROMINSTANCE ="Copy_of_Census_data" FROMINSTANCETYPE ="Source Definition" TOFIELD ="AREA" TOINSTANCE ="SQ_Copy_of_Census_data" TOINSTANCETYPE ="Source Qualifier"/>
        <CONNECTOR FROMFIELD ="CITY" FROMINSTANCE ="Copy_of_Census_data" FROMINSTANCETYPE ="Source Definition" TOFIELD ="CITY" TOINSTANCE ="SQ_Copy_of_Census_data" TOINSTANCETYPE ="Source Qualifier"/>
        <CONNECTOR FROMFIELD ="PERSON_ID" FROMINSTANCE ="SQ_Copy_of_Census_data" FROMINSTANCETYPE ="Source Qualifier" TOFIELD ="PERSON_ID" TOINSTANCE ="EXPTRANS" TOINSTANCETYPE ="Expression"/>
        <CONNECTOR FROMFIELD ="DOOR_NUMBER" FROMINSTANCE ="SQ_Copy_of_Census_data" FROMINSTANCETYPE ="Source Qualifier" TOFIELD ="DOOR_NUMBER" TOINSTANCE ="EXPTRANS" TOINSTANCETYPE ="Expression"/>
        <CONNECTOR FROMFIELD ="GENDER" FROMINSTANCE ="SQ_Copy_of_Census_data" FROMINSTANCETYPE ="Source Qualifier" TOFIELD ="GENDER" TOINSTANCE ="EXPTRANS" TOINSTANCETYPE ="Expression"/>
        <CONNECTOR FROMFIELD ="DOB" FROMINSTANCE ="SQ_Copy_of_Census_data" FROMINSTANCETYPE ="Source Qualifier" TOFIELD ="DOB" TOINSTANCE ="EXPTRANS" TOINSTANCETYPE ="Expression"/>
        <CONNECTOR FROMFIELD ="CURRENT_MARRTIAL_STATUS" FROMINSTANCE ="SQ_Copy_of_Census_data" FROMINSTANCETYPE ="Source Qualifier" TOFIELD ="CURRENT_MARRTIAL_STATUS" TOINSTANCE ="EXPTRANS" TOINSTANCETYPE ="Expression"/>
        <CONNECTOR FROMFIELD ="RELIGION" FROMINSTANCE ="SQ_Copy_of_Census_data" FROMINSTANCETYPE ="Source Qualifier" TOFIELD ="RELIGION" TOINSTANCE ="EXPTRANS" TOINSTANCETYPE ="Expression"/>
        <CONNECTOR FROMFIELD ="CASTE" FROMINSTANCE ="SQ_Copy_of_Census_data" FROMINSTANCETYPE ="Source Qualifier" TOFIELD ="CASTE" TOINSTANCE ="EXPTRANS" TOINSTANCETYPE ="Expression"/>
        <CONNECTOR FROMFIELD ="DISABILITY" FROMINSTANCE ="SQ_Copy_of_Census_data" FROMINSTANCETYPE ="Source Qualifier" TOFIELD ="DISABILITY" TOINSTANCE ="EXPTRANS" TOINSTANCETYPE ="Expression"/>
        <CONNECTOR FROMFIELD ="TYPE_OF_DISABILITY" FROMINSTANCE ="SQ_Copy_of_Census_data" FROMINSTANCETYPE ="Source Qualifier" TOFIELD ="TYPE_OF_DISABILITY" TOINSTANCE ="EXPTRANS" TOINSTANCETYPE ="Expression"/>
        <CONNECTOR FROMFIELD ="LITERACY_STATUS" FROMINSTANCE ="SQ_Copy_of_Census_data" FROMINSTANCETYPE ="Source Qualifier" TOFIELD ="LITERACY_STATUS" TOINSTANCE ="EXPTRANS" TOINSTANCETYPE ="Expression"/>
        <CONNECTOR FROMFIELD ="CURRENTSTATUS_OF_ATTENDANCE" FROMINSTANCE ="SQ_Copy_of_Census_data" FROMINSTANCETYPE ="Source Qualifier" TOFIELD ="CURRENTSTATUS_OF_ATTENDANCE" TOINSTANCE ="EXPTRANS" TOINSTANCETYPE ="Expression"/>
        <CONNECTOR FROMFIELD ="HIGHEST_EDUCATION_LEVEL" FROMINSTANCE ="SQ_Copy_of_Census_data" FROMINSTANCETYPE ="Source Qualifier" TOFIELD ="HIGHEST_EDUCATION_LEVEL" TOINSTANCE ="EXPTRANS" TOINSTANCETYPE ="Expression"/>
        <CONNECTOR FROMFIELD ="OCCUPATION" FROMINSTANCE ="SQ_Copy_of_Census_data" FROMINSTANCETYPE ="Source Qualifier" TOFIELD ="OCCUPATION" TOINSTANCE ="EXPTRANS" TOINSTANCETYPE ="Expression"/>
        <CONNECTOR FROMFIELD ="NATURE_OF_INDUSTRY" FROMINSTANCE ="SQ_Copy_of_Census_data" FROMINSTANCETYPE ="Source Qualifier" TOFIELD ="NATURE_OF_INDUSTRY" TOINSTANCE ="EXPTRANS" TOINSTANCETYPE ="Expression"/>
        <CONNECTOR FROMFIELD ="SECTOR" FROMINSTANCE ="SQ_Copy_of_Census_data" FROMINSTANCETYPE ="Source Qualifier" TOFIELD ="SECTOR" TOINSTANCE ="EXPTRANS" TOINSTANCETYPE ="Expression"/>
        <CONNECTOR FROMFIELD ="SALARY" FROMINSTANCE ="SQ_Copy_of_Census_data" FROMINSTANCETYPE ="Source Qualifier" TOFIELD ="SALARY" TOINSTANCE ="EXPTRANS" TOINSTANCETYPE ="Expression"/>
        <CONNECTOR FROMFIELD ="MODE_OF_TRAVELLING_TO_WORK_PLACE" FROMINSTANCE ="SQ_Copy_of_Census_data" FROMINSTANCETYPE ="Source Qualifier" TOFIELD ="MODE_OF_TRAVELLING_TO_WORK_PLACE" TOINSTANCE ="EXPTRANS" TOINSTANCETYPE ="Expression"/>
        <CONNECTOR FROMFIELD ="CHILDREN_SURVIVING" FROMINSTANCE ="SQ_Copy_of_Census_data" FROMINSTANCETYPE ="Source Qualifier" TOFIELD ="CHILDREN_SURVIVING" TOINSTANCE ="EXPTRANS" TOINSTANCETYPE ="Expression"/>
        <CONNECTOR FROMFIELD ="CHILDREN_EVER_BORN" FROMINSTANCE ="SQ_Copy_of_Census_data" FROMINSTANCETYPE ="Source Qualifier" TOFIELD ="CHILDREN_EVER_BORN" TOINSTANCE ="EXPTRANS" TOINSTANCETYPE ="Expression"/>
        <CONNECTOR FROMFIELD ="NUMBER_OF_PERSONS_EXPIRED_IN_LAST_10_YEARS" FROMINSTANCE ="SQ_Copy_of_Census_data" FROMINSTANCETYPE ="Source Qualifier" TOFIELD ="NUMBER_OF_PERSONS_EXPIRED_IN_LAST_10_YEARS" TOINSTANCE ="EXPTRANS" TOINSTANCETYPE ="Expression"/>
        <CONNECTOR FROMFIELD ="TYPE_OF_HOUSE" FROMINSTANCE ="SQ_Copy_of_Census_data" FROMINSTANCETYPE ="Source Qualifier" TOFIELD ="TYPE_OF_HOUSE" TOINSTANCE ="EXPTRANS" TOINSTANCETYPE ="Expression"/>
        <CONNECTOR FROMFIELD ="PAN_CARD" FROMINSTANCE ="SQ_Copy_of_Census_data" FROMINSTANCETYPE ="Source Qualifier" TOFIELD ="PAN_CARD" TOINSTANCE ="EXPTRANS" TOINSTANCETYPE ="Expression"/>
        <CONNECTOR FROMFIELD ="RATION_CARD" FROMINSTANCE ="SQ_Copy_of_Census_data" FROMINSTANCETYPE ="Source Qualifier" TOFIELD ="RATION_CARD" TOINSTANCE ="EXPTRANS" TOINSTANCETYPE ="Expression"/>
        <CONNECTOR FROMFIELD ="ADHAR_CARD" FROMINSTANCE ="SQ_Copy_of_Census_data" FROMINSTANCETYPE ="Source Qualifier" TOFIELD ="ADHAR_CARD" TOINSTANCE ="EXPTRANS" TOINSTANCETYPE ="Expression"/>
        <CONNECTOR FROMFIELD ="AREA" FROMINSTANCE ="SQ_Copy_of_Census_data" FROMINSTANCETYPE ="Source Qualifier" TOFIELD ="AREA" TOINSTANCE ="EXPTRANS" TOINSTANCETYPE ="Expression"/>
        <CONNECTOR FROMFIELD ="CITY" FROMINSTANCE ="SQ_Copy_of_Census_data" FROMINSTANCETYPE ="Source Qualifier" TOFIELD ="CITY" TOINSTANCE ="EXPTRANS" TOINSTANCETYPE ="Expression"/>
        <TARGETLOADORDER ORDER ="1" TARGETINSTANCE ="CENSUS_DATA_TGT_STG"/>
        <ERPINFO/>
    </MAPPING>
</FOLDER>
</REPOSITORY>
</POWERMART>